eegunity/__init__.py
eegunity/_share_attributes.py
eegunity/unifieddataset.py
eegunity/modules/__init__.py
eegunity/modules/batch/__init__.py
eegunity/modules/batch/eeg_batch.py
eegunity/modules/batch/eeg_scores_modified_mne.py
eegunity/modules/batch/eeg_scores_shady.py
eegunity/modules/batch/method_mixin_epoch.py
eegunity/modules/batch/utils.py
eegunity/modules/correction/__init__.py
eegunity/modules/correction/eeg_correction.py
eegunity/modules/llm_booster/__init__.py
eegunity/modules/llm_booster/eeg_llm_booster.py
eegunity/modules/llm_booster/eeg_llm_des_parser.py
eegunity/modules/llm_booster/eeg_llm_file_parser.py
eegunity/modules/parser/__init__.py
eegunity/modules/parser/eeg_parser.py
eegunity/modules/parser/eeg_parser_config.py
eegunity/modules/parser/eeg_parser_csv.py
eegunity/modules/parser/eeg_parser_mat.py
eegunity/resources/__init__.py
eegunity/resources/combined_montage.json
eegunity/utils/__init__.py
eegunity/utils/channel_align_raw.py
eegunity/utils/con_udatasets.py
eegunity/utils/h5.py
eegunity/utils/handle_errors.py
eegunity/utils/log_processing.py
eegunity/utils/normalize.py
eegunity/utils/pipeline.py
eegunity/utils/split_hdf5_file.py
eegunity-0.5.4.dist-info/licenses/LICENSE
eegunity-0.5.4.dist-info/METADATA
eegunity-0.5.4.dist-info/WHEEL
eegunity-0.5.4.dist-info/top_level.txt
eegunity-0.5.4.dist-info/RECORD
