Metadata-Version: 2.4
Name: eegunity
Version: 0.5.4
Summary: An open source Python pacakge for large-scale EEG datasets processing
Home-page: https://github.com/Baizhige/EEGUnity
Author: EEGUnity Team
Author-email: chengxuan.qin@outlook.com
Classifier: Programming Language :: Python :: 3
Classifier: License :: OSI Approved :: MIT License
Classifier: Operating System :: OS Independent
Requires-Python: >=3.7, <3.13
License-File: LICENSE
Requires-Dist: mne>=1.5.1
Requires-Dist: numpy<2.0.0,>=1.21.0
Requires-Dist: matplotlib>=3.7.3
Requires-Dist: h5py>=3.12.1
Requires-Dist: openai==1.35.1
Requires-Dist: pdfplumber>=0.11.4
Requires-Dist: pandas>=2.1.3
Requires-Dist: scipy>=1.11.2
Dynamic: author
Dynamic: author-email
Dynamic: classifier
Dynamic: description
Dynamic: description-content-type
Dynamic: home-page
Dynamic: license-file
Dynamic: requires-dist
Dynamic: requires-python
Dynamic: summary
